pygments_dracula/__init__.py
pygments_dracula/dracula.py
pygments_dracula-0.1.dist-info/METADATA
pygments_dracula-0.1.dist-info/RECORD
pygments_dracula-0.1.dist-info/WHEEL
pygments_dracula-0.1.dist-info/entry_points.txt
pygments_dracula-0.1.dist-info/top_level.txt
